models/__init__.py
models/fixture.py
models/league.py
models/player.py
models/team.py
calcioquery_common-0.2.dist-info/METADATA
calcioquery_common-0.2.dist-info/WHEEL
calcioquery_common-0.2.dist-info/top_level.txt
calcioquery_common-0.2.dist-info/RECORD
