Metadata-Version: 2.2
Name: calcioquery_common
Version: 0.2
Summary: Test
Requires-Python: >=3.10
Requires-Dist: pydantic>=2.10.6
